{
  "$schema": "https://raw.githubusercontent.com/Outer-Wilds-New-Horizons/new-horizons/main/NewHorizons/Schemas/body_schema.json",
  "name": "Bright Spark",
  "starSystem": "Jam5",
  "removeChildren": [ "Sector/Star/Audio_Star/SurfaceAudio_Sun"],
  "Base": {
    "gravityFallOff": "linear",
    "surfaceSize": 100,
    "surfaceGravity": 10,
    "centerOfSolarSystem": true
  },
  "Orbit": {
    "staticPosition": {
      "x": 1000,
      "y": 2000,
      "z": 5000
    }
  },
  "Star": {
    "stellarDeathType": "supernova",
    "size": 0.01,
    "solarLuminosity": 0,
    "supernovaSize": 2400,
    "supernovaSpeed": 200
  },
  "ShipLog": {
    "xmlFile": "planets/shiplog/AuthorModSystem.xml",
    "spriteFolder": "planets/shiplog/sprites"
  },
  "MapMarker": {
      "enabled": true
  }
}